<?xml version="1.0" encoding="UTF-8"?>

<properties usagelabel="File Details">
<property id="name" />
<property id="assetviews" />
<property id="assetvotes"  />
<property id="imageorientation" />
<property id="length"  />
<property id="framerate" />
<property id="bitspersample" />
<property id="compression" />
<property id="cammaker" />
<property id="cammodel"/> 
<property id="xresolution" />
<property id="yresolution" />
<property id="artist" />
<property id="comment" />
<property id="contributor" />
<property id="creator" />
<property id="source" />
<property id="iso"/>
<property id="author" />
<property id="localpath" />
<property id="importstatus" />
<property id="fileformat" />
<property id="filesize" />
<property id="colortype" />
<property id="width"  />
<property id="height"  />
<property id="assetcreationdate" />
<property id="assetmodificationdate" />
<property id="recordmodificationdate"/>
<property id="assetaddeddate" />
<property id="editstatus" />
<property id="owner"  />
</properties>
