<properties>
	<property id="id" index="true" stored="true"  keyword="true" internalfield="true" >ID</property>
	<property id="userid" index="true" stored="true"  internalfield="true">User Id</property>
	<property id="settingsgroup" editable="true" index="true" stored="true" datatype="list">Role</property>
	<property id="view_asset_resultstable" index="true" stored="true"  internalfield="true" >View Table Results</property>
	<property id="profilesearchfilters" index="true" stored="true"  internalfield="true" >Filters Used By Search</property>
	<property id="hideassettype" index="true" stored="true"  internalfield="true" >Hide Asset Types</property>
	<property id="maximize_screen" index="true" stored="true"  internalfield="true" >Maximize</property>
	<property id="sourcepath" index="true" stored="true"  internalfield="true">Source Path</property>	
	<property id="last_selected_module" index="true" stored="true"  internalfield="true">Last Selected Module</property>
	<property id="last_selected_library" index="true" stored="true"  internalfield="true">Last Selected Library</property>
	<property id="maximize_player" index="true" stored="true"  internalfield="true">false</property>
	<property id="expand_media_sidebar" index="true" stored="true"  internalfield="true">true</property>
	
	<property id="assethitsperpage" index="true" stored="true" type="list" listid="hitcount" editable="true" >Number of Assets to view per page</property>
	<property id="modulehitsperpage" index="true" stored="true" type="list" listid="hitcount" editable="true" >Number of rows show on Module results</property>
	
	<!--  Custom fields -->

    <property id="phone" index="true" stored="true" keyword="true" editable="true">Phone</property>
    
    <property id="business" index="true" stored="true" keyword="true" editable="true">Business / Affiliation Name</property>
    <property id="jobtitle" index="true" stored="true" keyword="true" editable="true">Job Title</property>
    <property id="country" index="true" stored="true" keyword="true" editable="true">Country</property>
    <property id="address1" index="true" stored="true" keyword="true" editable="true">Address 1</property> 
    <property id="address2" index="true" stored="true" keyword="true" editable="true">Address 2</property>
    <property id="city" index="true" stored="true" keyword="true" editable="true">City</property>
    <property id="state_province" index="true" stored="true" keyword="true" editable="true">State / Province</property>
    <property id="postal_code" index="true" stored="true" keyword="true" editable="true">Postal Code</property>
	
	<property id="screenname" index="true" stored="true" keyword="true" editable="true">Screen Name</property>
	<property id="firstName" index="true" stored="true" keyword="true" editable="true" required="true">First Name</property>
	<property id="lastName" index="true" stored="true" keyword="true" editable="true" required="true">Last Name</property>
	<property id="enabled" index="true" stored="true" keyword="true" editable="true" type="boolean">Enabled</property>
	
	<property id="password" index="true" stored="true" keyword="true" editable="true" viewtype="password">Password</property>
	
	
</properties>
