<properties>
	<property id="id" />
	<property id="name" />
	
	<property id="publishtype"  />
	<property id="notifyadmin" />
	<property id="server" note="IP or server name" />
	<property id="url" note="Path to saved files"/>
	
	<property id="username" />
	<property id="password" note="Optional, defaults to user password" />
	<property id="convertpreset" viewtype="multiselect"/>

	<property id="onimport" />
	<property id="remotempublish" />
	<property id="onlyremotempublish" />
	
	<property id="bucket" note="Amazon bucket"/>
	<property id="accesskey" note="Amazon Key" />
	<property id="secretkey" note="Amazon Secret Key" />

	<property id="administrativecontact" />
	<property id="administrativeemail" />
	
	<!-- This stuff is dumb
	
	<property id="company" />
	<property id="division" />
		
	<property id="technicalcontact" />
	<property id="technicalphone" />
	<property id="technicalemail" />

	<property id="administrativecontact" />
	<property id="administrativephone" />
	<property id="administrativeemail" />
	
	<property id="emergencycontact" />
	<property id="emergencyphone" />
	<property id="emergencyemail" />
 -->
	
</properties>